{"cameraMode":{"drawMode":0,"name":"Shaded","section":"Shading Mode"},"sceneLighting":true,"audioPlay":false,"sceneViewState":{"m_AlwaysRefresh":false,"showFog":true,"showSkybox":true,"showFlares":true,"showImageEffects":true,"showParticleSystems":true,"showVisualEffectGraphs":true,"m_FxEnabled":true},"in2DMode":false,"pivot":{"x":8.802352905273438,"y":1.5910091400146485,"z":-5.546176910400391},"rotation":{"x":-0.019358355551958085,"y":0.9773135781288147,"z":-0.18421943485736848,"w":-0.10269938409328461},"size":33.16360092163086,"orthographic":false}